examples/agent_history_basic.py
examples/agent_tool_usage_benchmark.py
examples/agent_with_mcp_tools.py
examples/agent_with_remote_mcp_sse.py
examples/chat_history_comparison.py
examples/chat_history_display.py
examples/create_workflow_using_architect.py
examples/eda.py
examples/hierarchical_structure.py
examples/history_loading.py
examples/history_loading_with_assistant_supervisor.py
examples/multi_argument_function_calling.py
examples/multi_logger.py
examples/multiple_tool_calls.py
examples/output_schema_examples.py
examples/schema_aware_workflow_example.py
examples/workflow_with_custom_id.py
examples/config_mcp_schema/config_mcp_schema.py
examples/memory_task_management/example_memory_management.py
examples/memory_task_management/task_tools.py
examples/supervisor_multi_mcp/add_server.py
examples/supervisor_multi_mcp/example_multi_mcp.py
examples/supervisor_multi_mcp/weather_server.py
examples/task_management_with_yaml/example_task_management.py
examples/task_management_with_yaml/task_tools.py
primisai/__init__.py
primisai/nexus/architect/__init__.py
primisai/nexus/architect/builder.py
primisai/nexus/architect/evaluator.py
primisai/nexus/architect/expander.py
primisai/nexus/architect/manager.py
primisai/nexus/architect/prompter.py
primisai/nexus/architect/prompts.py
primisai/nexus/architect/schemas.py
primisai/nexus/architect/structurer.py
primisai/nexus/config/__init__.py
primisai/nexus/config/agent_factory.py
primisai/nexus/config/config_validator.py
primisai/nexus/config/yaml_config.py
primisai/nexus/core/__init__.py
primisai/nexus/core/agents.py
primisai/nexus/core/ai.py
primisai/nexus/core/supervisor.py
primisai/nexus/history/__init__.py
primisai/nexus/history/history_manager.py
primisai/nexus/tools/tool_functions.py
primisai/nexus/utils/__init__.py
primisai/nexus/utils/debugger.py
primisai-0.8.1.dist-info/licenses/LICENSE
scripts/sync_dependencies.py
test/test_hierarchical_structure.py
primisai-0.8.1.dist-info/METADATA
primisai-0.8.1.dist-info/WHEEL
primisai-0.8.1.dist-info/top_level.txt
primisai-0.8.1.dist-info/RECORD
