Metadata-Version: 2.4
Name: primisai
Version: 0.8.1
Summary: Nexus is a powerful and flexible Python package for managing AI agents and coordinating complex tasks using LLMs.
Author-email: PrimisAI <info@primis.ai>
License: MIT
Project-URL: changelog, https://github.com/PrimisAI/nexus/blob/main/CHANGELOG.md
Project-URL: homepage, https://github.com/PrimisAI/nexus
Project-URL: issues, https://github.com/PrimisAI/nexus/issues
Project-URL: repository, https://github.com/PrimisAI/nexus.git
Keywords: AI,LLM,framework,AI agents
Classifier: Programming Language :: Python :: 3
Classifier: License :: OSI Approved :: MIT License
Classifier: Operating System :: OS Independent
Requires-Python: >=3.10
License-File: LICENSE
Requires-Dist: openai==1.66.3
Requires-Dist: python-dotenv==1.0.1
Requires-Dist: streamlit>=1.38.0
Requires-Dist: pytest==8.3.4
Requires-Dist: PyYAML==6.0.2
Requires-Dist: mcp[cli]>=1.10.0
Dynamic: license-file
